pdhttp/__init__.py
pdhttp/api_client.py
pdhttp/configuration.py
pdhttp/rest.py
pdhttp/api/__init__.py
pdhttp/api/base_api.py
pdhttp/api/default_api.py
pdhttp/api/environment_api.py
pdhttp/api/gripper_api.py
pdhttp/api/other_api.py
pdhttp/api/pose_api.py
pdhttp/api/position_api.py
pdhttp/api/robot_api.py
pdhttp/api/signals_api.py
pdhttp/api/status_api.py
pdhttp/api/tool_api.py
pdhttp/api/version_api.py
pdhttp/models/__init__.py
pdhttp/models/box_obstacle.py
pdhttp/models/capsule_obstacle.py
pdhttp/models/error400.py
pdhttp/models/error_emergency503.py
pdhttp/models/error_port412.py
pdhttp/models/error_pose412.py
pdhttp/models/error_position412.py
pdhttp/models/failure.py
pdhttp/models/failure_level.py
pdhttp/models/failure_type.py
pdhttp/models/gripper_robot_action.py
pdhttp/models/interpolation_type.py
pdhttp/models/jogging_acceleration.py
pdhttp/models/jogging_acceleration_acceleration.py
pdhttp/models/joint_motion_parameters.py
pdhttp/models/joint_poses.py
pdhttp/models/joint_positions.py
pdhttp/models/linear_motion_parameters.py
pdhttp/models/linear_poses.py
pdhttp/models/linear_positions.py
pdhttp/models/motion_status.py
pdhttp/models/motion_type.py
pdhttp/models/motor_status.py
pdhttp/models/obstacle.py
pdhttp/models/output_robot_action.py
pdhttp/models/plane_obstacle.py
pdhttp/models/point.py
pdhttp/models/pose.py
pdhttp/models/pose_timestamp.py
pdhttp/models/position.py
pdhttp/models/position_timestamp.py
pdhttp/models/recover_state.py
pdhttp/models/robot_action.py
pdhttp/models/robot_action_type.py
pdhttp/models/robot_info.py
pdhttp/models/rotation.py
pdhttp/models/session.py
pdhttp/models/signal.py
pdhttp/models/simplified_capsule_obstacle.py
pdhttp/models/system_state.py
pdhttp/models/tool_info.py
pdhttp/models/tool_shape.py
pdhttp/models/version.py
pdhttp/models/wrist_button_state.py
pdhttp/models/wrist_button_states.py
pdhttp-1.8.4.dist-info/LICENSE
pdhttp-1.8.4.dist-info/METADATA
pdhttp-1.8.4.dist-info/WHEEL
pdhttp-1.8.4.dist-info/top_level.txt
pdhttp-1.8.4.dist-info/RECORD
